spatialiteintrospect/__init__.py
spatialiteintrospect/introspect.py
spatialiteintrospect/metadata.py
spatialiteintrospect-1.2.dist-info/DESCRIPTION.rst
spatialiteintrospect-1.2.dist-info/METADATA
spatialiteintrospect-1.2.dist-info/RECORD
spatialiteintrospect-1.2.dist-info/WHEEL
spatialiteintrospect-1.2.dist-info/metadata.json
spatialiteintrospect-1.2.dist-info/top_level.txt
