Metadata-Version: 2.0
Name: spatialiteintrospect
Version: 1.2
Summary: Python library for easily retrieving table names, geometry columns, geometry tables, etc from a Spatialite database
Home-page: https://github.com/scolab-dot-eu/spatialite-introspect
Author: Cesar Martinez Izquierdo
Author-email: UNKNOWN
License: UNKNOWN
Platform: UNKNOWN
Classifier: Development Status :: 4 - Beta
Classifier: Environment :: Console
Classifier: Intended Audience :: Developers
Classifier: License :: OSI Approved :: GNU Affero General Public License v3
Classifier: Natural Language :: English
Classifier: Operating System :: OS Independent
Classifier: Programming Language :: Python :: 2
Classifier: Programming Language :: Python :: 2.6
Classifier: Programming Language :: Python :: 2.7
Classifier: Programming Language :: Python :: 3
Classifier: Topic :: Database
Classifier: Topic :: Software Development :: Libraries :: Python Modules
